django_ssify-0.2.6.dist-info/DESCRIPTION.rst
django_ssify-0.2.6.dist-info/METADATA
django_ssify-0.2.6.dist-info/RECORD
django_ssify-0.2.6.dist-info/WHEEL
django_ssify-0.2.6.dist-info/metadata.json
django_ssify-0.2.6.dist-info/top_level.txt
ssify/__init__.py
ssify/cache.py
ssify/cache_backends.py
ssify/conf.py
ssify/decorators.py
ssify/exceptions.py
ssify/middleware.py
ssify/middleware_debug.py
ssify/models.py
ssify/serializers.py
ssify/utils.py
ssify/variables.py
ssify/version.py
ssify/management/__init__.py
ssify/management/commands/__init__.py
ssify/management/commands/ssify_nginx_conf.py
ssify/templates/ssify/csrf_token.html
ssify/templatetags/__init__.py
ssify/templatetags/ssify.py
